cagpaint/__init__.py
cagpaint/setup.py
cagpaint/painter/__init__.py
cagpaint/painter/install_fixes.py
cagpaint/painter/src/__init__.py
cagpaint/painter/src/about.py
cagpaint/painter/src/contrast_slider.py
cagpaint/painter/src/create_project.py
cagpaint/painter/src/file_utils.py
cagpaint/painter/src/graphics_scene.py
cagpaint/painter/src/graphics_view.py
cagpaint/painter/src/im_utils.py
cagpaint/painter/src/im_viewer.py
cagpaint/painter/src/instructions.py
cagpaint/painter/src/lock.py
cagpaint/painter/src/main.py
cagpaint/painter/src/menus.py
cagpaint/painter/src/name_edit_widget.py
cagpaint/painter/src/nav.py
cagpaint/painter/src/palette.py
cagpaint/painter/src/patch_seg.py
cagpaint/painter/src/progress_widget.py
cagpaint/painter/src/root_painter.py
cagpaint/painter/src/segment.py
cagpaint/painter/src/segment_folder.py
cagpaint/painter/src/slice_nav.py
cagpaint/painter/src/tcp_utils.py
cagpaint/painter/src/view_state.py
cagpaint/painter/src/visibility_widget.py
cagpaint/trainer/__init__.py
cagpaint/trainer/data_utils.py
cagpaint/trainer/datasets.py
cagpaint/trainer/file_utils.py
cagpaint/trainer/im_utils.py
cagpaint/trainer/instructions.py
cagpaint/trainer/loss.py
cagpaint/trainer/main.py
cagpaint/trainer/metrics.py
cagpaint/trainer/model_utils.py
cagpaint/trainer/patch_seg.py
cagpaint/trainer/scp_utils.py
cagpaint/trainer/startup.py
cagpaint/trainer/trainer.py
cagpaint/trainer/unet3d.py
cagpaint-0.2.0.dist-info/LICENSE
cagpaint-0.2.0.dist-info/METADATA
cagpaint-0.2.0.dist-info/WHEEL
cagpaint-0.2.0.dist-info/top_level.txt
cagpaint-0.2.0.dist-info/RECORD
