Metadata-Version: 2.1
Name: cagpaint
Version: 0.2.0
Summary: cagpaint
Home-page: https://github.com/yourusername/your-package
Author: ChristianEschen
Author-email: christian_eschen@hotmail.com
License-File: LICENSE
